gym_gridworlds/__init__.py
gym_gridworlds/envs/__init__.py
gym_gridworlds/envs/cliff_env.py
gym_gridworlds/envs/gridworld_env.py
gym_gridworlds/envs/windy_gridworld_env.py
gym_gridworlds-0.0.2.dist-info/DESCRIPTION.rst
gym_gridworlds-0.0.2.dist-info/METADATA
gym_gridworlds-0.0.2.dist-info/RECORD
gym_gridworlds-0.0.2.dist-info/WHEEL
gym_gridworlds-0.0.2.dist-info/metadata.json
gym_gridworlds-0.0.2.dist-info/top_level.txt
