Metadata-Version: 2.0
Name: gym-gridworlds
Version: 0.0.2
Summary: Gridworlds environments for OpenAI gym.
Home-page: https://github.com/podondra/gym-gridworlds
Author: Ondřej Podsztavek
Author-email: ondrej.podsztavek@gmail.com
License: MIT License
Platform: UNKNOWN
Requires-Dist: gym
Requires-Dist: numpy
